{
  "name": "tokens",
  "type": "registry:lib",
  "title": "Tokens",
  "description": "Semantic tokens with the shadcn-default palette + Unistyles theme configuration.",
  "dependencies": [
    "react-native-unistyles@^3.2.0",
    "react-native-nitro-modules@^0.35.2"
  ],
  "files": [
    {
      "path": "lib/tokens/types.ts",
      "content": "/**\n * Type-only re-exports for the semantic theme contract.\n *\n * Importing types from here (instead of a concrete theme file like\n * `shadcn-default.js`) makes intent explicit — the consumer wants the\n * contract, not the values — and is friendlier to tools that strip\n * type-only imports at build time. The `Theme` type is canonical: every\n * theme palette (shadcn-default, future shadcn-rose, custom brand palettes)\n * must produce values that satisfy it.\n */\nexport type { Theme, ThemeName } from \"./shadcn-default\"\n",
      "type": "registry:lib"
    },
    {
      "path": "lib/tokens/shadcn-default.ts",
      "content": "import { Platform } from \"react-native\"\n\n/**\n * Leshi UI — `shadcn-default` theme.\n *\n * This palette mirrors shadcn/ui's default \"zinc / neutral\" baseColor: cool\n * grays for surfaces, near-white primary on light, near-black primary on dark.\n * It is the recommended starting point for new Leshi UI projects.\n *\n * The file name (`shadcn-default.ts`) is the theme's identity. To ship another\n * theme (e.g. `shadcn-rose`, `shadcn-blue`, or a custom brand palette), add a\n * sibling file under `core/tokens/` and publish it as its own registry item.\n * Geometry, typography, and spacing tokens are shared across themes — only the\n * `lightTheme.colors` / `darkTheme.colors` blocks differ.\n *\n * Identity:\n */\nexport const THEME_NAME = \"shadcn-default\" as const\n\n/**\n * Font family stacks.\n *\n * React Native's `\"System\"` keyword resolves to the platform default font on\n * iOS / Android, but on React Native Web it gets passed through to CSS\n * verbatim — and `font-family: System` is not a valid CSS font, so browsers\n * fall back to their serif default. Each platform therefore picks the right\n * shape:\n *\n * - native: the `\"System\"` keyword (mapped by RN to SF Pro / Roboto / etc.).\n * - web: a CSS font stack matching what React Native Web emits for default\n *   <Text>, so theme-typed text visually matches unstyled <Text>.\n *\n * The web stacks deliberately avoid quoted entries that contain another\n * quoted entry as a substring (e.g. having both `\"Segoe UI\"` and\n * `\"Segoe UI Emoji\"` simultaneously). Unistyles' web serializer mangles the\n * second one when this happens — `\"Segoe UI Emoji\"` came out as `UI Emoji\"`\n * with an unclosed quote, invalidating the entire CSS value and forcing the\n * browser to its serif default. Modern -apple-system / system-ui already\n * renders emoji natively, so dropping the explicit emoji fallback is safe.\n */\nconst sansFamily = Platform.select({\n  web: '-apple-system, BlinkMacSystemFont, \"Segoe UI\", Roboto, Helvetica, Arial, sans-serif',\n  default: \"System\",\n}) as string\n\nconst monoFamily = Platform.select({\n  web: \"ui-monospace, SFMono-Regular, Menlo, Monaco, Consolas, monospace\",\n  default: \"Menlo\",\n}) as string\n\n/**\n * The core design tokens for Leshi UI.\n *\n * These tokens define the shared geometry, typography, and spacing used across\n * all components. Color values live in `lightTheme.colors` and `darkTheme.colors`\n * below; everything else is shared between themes.\n */\nexport const tokens = {\n  /** Border radius presets. */\n  radius: {\n    sm: 6,\n    md: 8,\n    lg: 12,\n  },\n  /** Typography configuration: font families, sizes, line heights, weights. */\n  typography: {\n    families: {\n      sans: sansFamily,\n      mono: monoFamily,\n    },\n    sizes: {\n      xs: 12,\n      sm: 14,\n      md: 16,\n      lg: 18,\n      xl: 20,\n    },\n    lineHeights: {\n      xs: 16,\n      sm: 20,\n      md: 24,\n      lg: 28,\n      xl: 30,\n    },\n    weights: {\n      normal: \"400\",\n      medium: \"500\",\n      semibold: \"600\",\n      bold: \"700\",\n    },\n  },\n  /** Spacing scale on a 4px grid. */\n  spacing: {\n    0: 0,\n    1: 4,\n    2: 8,\n    3: 12,\n    4: 16,\n    5: 20,\n    6: 24,\n    8: 32,\n    10: 40,\n    12: 48,\n    16: 64,\n    20: 80,\n    24: 96,\n  },\n} as const\n\n/**\n * Default light theme.\n */\nexport const lightTheme = {\n  ...tokens,\n  colors: {\n    background: \"hsl(0, 0%, 100%)\",\n    foreground: \"hsl(240, 10%, 3.9%)\",\n    card: \"hsl(0, 0%, 100%)\",\n    cardForeground: \"hsl(240, 10%, 3.9%)\",\n    popover: \"hsl(0, 0%, 100%)\",\n    popoverForeground: \"hsl(240, 10%, 3.9%)\",\n    primary: \"hsl(240, 5.9%, 10%)\",\n    primaryForeground: \"hsl(0, 0%, 98%)\",\n    secondary: \"hsl(240, 4.8%, 95.9%)\",\n    secondaryForeground: \"hsl(240, 5.9%, 10%)\",\n    muted: \"hsl(240, 4.8%, 95.9%)\",\n    mutedForeground: \"hsl(240, 3.8%, 46.1%)\",\n    accent: \"hsl(240, 4.8%, 95.9%)\",\n    accentForeground: \"hsl(240, 5.9%, 10%)\",\n    destructive: \"hsl(0, 84.2%, 60.2%)\",\n    destructiveForeground: \"hsl(0, 0%, 98%)\",\n    border: \"hsl(240, 5.9%, 90%)\",\n    input: \"hsl(240, 5.9%, 90%)\",\n    ring: \"hsl(240, 10%, 3.9%)\",\n  },\n} as const\n\n/**\n * Default dark theme.\n */\nexport const darkTheme = {\n  ...tokens,\n  colors: {\n    background: \"hsl(240, 10%, 3.9%)\",\n    foreground: \"hsl(0, 0%, 98%)\",\n    card: \"hsl(240, 10%, 3.9%)\",\n    cardForeground: \"hsl(0, 0%, 98%)\",\n    popover: \"hsl(240, 10%, 3.9%)\",\n    popoverForeground: \"hsl(0, 0%, 98%)\",\n    primary: \"hsl(0, 0%, 98%)\",\n    primaryForeground: \"hsl(240, 5.9%, 10%)\",\n    secondary: \"hsl(240, 3.7%, 15.9%)\",\n    secondaryForeground: \"hsl(0, 0%, 98%)\",\n    muted: \"hsl(240, 3.7%, 15.9%)\",\n    mutedForeground: \"hsl(240, 5%, 64.9%)\",\n    accent: \"hsl(240, 3.7%, 15.9%)\",\n    accentForeground: \"hsl(0, 0%, 98%)\",\n    destructive: \"hsl(0, 62.8%, 30.6%)\",\n    destructiveForeground: \"hsl(0, 0%, 98%)\",\n    border: \"hsl(240, 3.7%, 15.9%)\",\n    input: \"hsl(240, 3.7%, 15.9%)\",\n    ring: \"hsl(240, 4.9%, 83.9%)\",\n  },\n} as const\n\n/**\n * The semantic theme contract.\n *\n * Every styling backend (Unistyles flavor, StyleSheet flavor, future flavors)\n * must produce themes that satisfy this shape. Geometry and typography fields\n * carry literal types via `typeof tokens.X` so backends like Unistyles can\n * infer variant keys from the values; color fields are generic strings because\n * the literal HSL strings are not load-bearing for the type system.\n */\nexport type Theme = {\n  radius: typeof tokens.radius\n  typography: typeof tokens.typography\n  spacing: typeof tokens.spacing\n  colors: {\n    background: string\n    foreground: string\n    card: string\n    cardForeground: string\n    popover: string\n    popoverForeground: string\n    primary: string\n    primaryForeground: string\n    secondary: string\n    secondaryForeground: string\n    muted: string\n    mutedForeground: string\n    accent: string\n    accentForeground: string\n    destructive: string\n    destructiveForeground: string\n    border: string\n    input: string\n    ring: string\n  }\n}\n\n/**\n * Built-in theme name. Consumers can extend via module augmentation.\n */\nexport type ThemeName = \"light\" | \"dark\"\n\n/**\n * Compute spacing on the 4px grid.\n *\n * @param value - Multiplier (e.g., 4 → 16px).\n * @returns Pixel value.\n */\nexport function space(value: number): number {\n  return value * 4\n}\n",
      "type": "registry:lib"
    },
    {
      "path": "lib/unistyles.ts",
      "content": "import { StyleSheet } from \"react-native-unistyles\"\n\n// Default palette is shadcn-default. To swap palettes, change this import to\n// another theme file (e.g. `./tokens/shadcn-rose.js`) — the rest of the file\n// stays the same.\nimport { darkTheme, lightTheme } from \"./tokens/shadcn-default\"\n\n/**\n * Unistyles initialization.\n *\n * Configures `react-native-unistyles` with the light and dark themes from\n * `core/tokens/`. Both themes share the same shape (`Theme` from\n * `core/tokens/types.ts`) so swapping themes at runtime is type-safe.\n *\n * IMPORTANT: import this module exactly once from the consumer's app entry\n * point BEFORE any component or stylesheet is imported. Failure to do so\n * results in Unistyles errors or unstyled content.\n *\n * For Expo Router, use a custom `index.ts` entry file and import this module\n * there. If using Expo static web rendering, also import it from\n * `app/+html.tsx` and render `useServerUnistyles()` inside that file's\n * `<head>`.\n */\nStyleSheet.configure({\n  themes: {\n    light: lightTheme,\n    dark: darkTheme,\n  },\n  settings: {\n    adaptiveThemes: true,\n  },\n})\n",
      "type": "registry:lib"
    },
    {
      "path": "lib/unistyles-types.d.ts",
      "content": "import type { Theme } from \"./tokens/types\"\n\ndeclare module \"react-native-unistyles\" {\n  export interface UnistylesThemes {\n    light: Theme\n    dark: Theme\n  }\n}\n",
      "type": "registry:lib"
    }
  ]
}
